structure_learning/__init__.py
structure_learning/causal_model.py
structure_learning/conditional_functions.py
structure_learning/contrib/__init__.py
structure_learning/contrib/demo_xges.py
structure_learning/distributions.py
structure_learning/graph.py
structure_learning/simulated.py
structure_learning/utils.py
structure_learning-0.1.0.dist-info/LICENSE
structure_learning-0.1.0.dist-info/METADATA
structure_learning-0.1.0.dist-info/WHEEL
structure_learning-0.1.0.dist-info/RECORD
